gnar/__init__.py
gnar/__main__.py
gnar/core.py
gnar/shell.py
gnar/builtins/__init__.py
gnar/builtins/str.py
gnar-0.1.2.dist-info/LICENSE
gnar-0.1.2.dist-info/METADATA
gnar-0.1.2.dist-info/WHEEL
gnar-0.1.2.dist-info/top_level.txt
gnar-0.1.2.dist-info/RECORD
