Metadata-Version: 2.1
Name: gnar
Version: 0.1.2
License-File: LICENSE
